DESCRIPTION
MANIFEST.in
README.md
setup.py
about_py/__init__.py
about_py/mixins.py
about_py/settings.py
about_py/urls.py
about_py/views.py
about_py/wsgi.py
about_py.egg-info/PKG-INFO
about_py.egg-info/SOURCES.txt
about_py.egg-info/dependency_links.txt
about_py.egg-info/not-zip-safe
about_py.egg-info/requires.txt
about_py.egg-info/top_level.txt
about_py/core/__init__.py
about_py/core/vcs.py
about_py/core/tests/__init__.py
about_py/core/tests/vcs_test.py
about_py/static/about_py/css/grid.css
about_py/static/about_py/css/style.css
about_py/static/about_py/img/back.png
about_py/static/about_py/img/blurry.jpg
about_py/static/about_py/img/botleft.png
about_py/static/about_py/img/botright.png
about_py/static/about_py/img/gradback.png
about_py/static/about_py/img/gradhead.png
about_py/static/about_py/img/gradhover.png
about_py/static/about_py/img/header.jpg
about_py/static/about_py/img/left.png
about_py/static/about_py/img/pattern-head.png
about_py/static/about_py/img/pattern.gif
about_py/static/about_py/img/pattern.png
about_py/static/about_py/img/patternb-head.png
about_py/static/about_py/img/patternb.png
about_py/static/about_py/img/right.png
about_py/templates/about_py/about.html
about_py/utils/__init__.py
about_py/utils/bunch.py
about_py/utils/exceptions.py