Metadata-Version: 1.0
Name: about-py
Version: 0.0.3
Summary: Makes a webpage available with information about the projects last version control system commits and
Home-page: https://github.com/ceasaro/about_py
Author: Cees van Wieringen
Author-email: ceesvw@gmail.com
License: UNKNOWN
Platform: UNKNOWN
